django_wafris/__init__.py
django_wafris/admin.py
django_wafris/apps.py
django_wafris/lua/wafris_core.lua
django_wafris/middleware.py
django_wafris/migrations/__init__.py
django_wafris/models.py
django_wafris/settings.py
django_wafris/tests.py
django_wafris/views.py
django_wafris/wafris_core.py
django_wafris-0.1.0.dist-info/LICENSE
django_wafris-0.1.0.dist-info/METADATA
django_wafris-0.1.0.dist-info/WHEEL
django_wafris-0.1.0.dist-info/RECORD
