Metadata-Version: 2.1
Name: django-wafris
Version: 0.1.0
Summary: Django Wafris
License: MIT
Author: Turkalp Burak Kayrancioglu
Author-email: bkayranci@gmail.com
Requires-Python: >=3.12,<4.0
Classifier: License :: OSI Approved :: MIT License
Classifier: Programming Language :: Python :: 3
Classifier: Programming Language :: Python :: 3.12
Requires-Dist: Django (>=5.1.1,<6.0.0)
Requires-Dist: redis (>=5.1.0,<6.0.0)
